[{"name":"Voomm","registered_number":2215552,"industry":"Radio And Television Broadcasting And Communications Equipment","address":"3 Pleasure Terrace","city":"Fumin","state":null,"country":"China","domain_name":"shop-pro.jp"},
    {"name":"Vimbo","registered_number":3507925,"industry":"n/a","address":"58561 Burning Wood Court","city":"Acatenango","state":null,"country":"Guatemala","domain_name":"comcast.net"},
    {"name":"Tagchat","registered_number":1402770,"industry":"n/a","address":"61 Buell Terrace","city":"Dzüünharaa","state":null,"country":"Mongolia","domain_name":"cbc.ca"},
    {"name":"Twitterbeat","registered_number":4105640,"industry":"Business Services","address":"20842 Browning Parkway","city":"Ejidal","state":"Guerrero","country":"Mexico","domain_name":"surveymonkey.com"},
    {"name":"Blogtag","registered_number":3097494,"industry":"Industrial Machinery/Components","address":"9 Brickson Park Junction","city":"Cunliji","state":null,"country":"China","domain_name":"uol.com.br"},
    {"name":"Kayveo","registered_number":7100404,"industry":"n/a","address":"1042 Algoma Plaza","city":"Taishanmiao","state":null,"country":"China","domain_name":"webs.com"},
    {"name":"Yamia","registered_number":6650155,"industry":"Restaurants","address":"4273 Knutson Point","city":"Yongfeng","state":null,"country":"China","domain_name":"soundcloud.com"},
    {"name":"Kazio","registered_number":6555739,"industry":"n/a","address":"15442 Emmet Junction","city":"Caballococha","state":null,"country":"Peru","domain_name":"marketwatch.com"},
    {"name":"Shufflebeat","registered_number":4478764,"industry":"Real Estate Investment Trusts","address":"5 Lindbergh Road","city":"Tân Phú","state":null,"country":"Vietnam","domain_name":"cnbc.com"},
    {"name":"Latz","registered_number":9464954,"industry":"Electric Utilities: Central","address":"519 Sunfield Junction","city":"Homa Bay","state":null,"country":"Kenya","domain_name":"pcworld.com"},
    {"name":"Trilia","registered_number":2747067,"industry":"n/a","address":"29 Northfield Drive","city":"Liulin","state":null,"country":"China","domain_name":"mozilla.org"},
    {"name":"Centidel","registered_number":6536065,"industry":"Building Materials","address":"56351 Surrey Place","city":"La Palma","state":"Guerrero","country":"Mexico","domain_name":"google.de"},
    {"name":"Aimbu","registered_number":3062859,"industry":"n/a","address":"182 Pepper Wood Trail","city":"Utena","state":null,"country":"Lithuania","domain_name":"live.com"},
    {"name":"Eire","registered_number":3450881,"industry":"Auto Manufacturing","address":"67194 Continental Street","city":"Togu","state":null,"country":"Indonesia","domain_name":"springer.com"},
    {"name":"Camido","registered_number":5391926,"industry":"Oil & Gas Production","address":"80228 Canary Avenue","city":"Bolou","state":null,"country":"Indonesia","domain_name":"buzzfeed.com"},
    {"name":"Cogibox","registered_number":1159648,"industry":"Major Pharmaceuticals","address":"8 Northport Pass","city":"Shawnee Mission","state":"Kansas","country":"United States","domain_name":"dot.gov"},
    {"name":"Katz","registered_number":5093159,"industry":"Hospital/Nursing Management","address":"94686 Hoard Crossing","city":"Langxi","state":null,"country":"China","domain_name":"rambler.ru"},
    {"name":"Brainsphere","registered_number":7198206,"industry":"n/a","address":"1708 Continental Trail","city":"Farmington","state":"Michigan","country":"United States","domain_name":"yellowbook.com"},
    {"name":"Meedoo","registered_number":4129797,"industry":"Property-Casualty Insurers","address":"16 Shasta Drive","city":"Bachok","state":"Kelantan","country":"Malaysia","domain_name":"google.com.au"},
    {"name":"Livepath","registered_number":4990622,"industry":"Meat/Poultry/Fish","address":"7 Aberg Crossing","city":"Novoorsk","state":null,"country":"Russia","domain_name":"twitpic.com"},
    {"name":"Yacero","registered_number":9148345,"industry":"Business Services","address":"468 Carioca Place","city":"Mao","state":null,"country":"Dominican Republic","domain_name":"domainmarket.com"},
    {"name":"Brightdog","registered_number":4812264,"industry":"Finance: Consumer Services","address":"2 Becker Junction","city":"Tân Hòa","state":null,"country":"Vietnam","domain_name":"ow.ly"},
    {"name":"Gabtune","registered_number":1223436,"industry":"Natural Gas Distribution","address":"655 International Trail","city":"Jönköping","state":"Jönköping","country":"Sweden","domain_name":"issuu.com"},
    {"name":"Devcast","registered_number":2292769,"industry":"Hospital/Nursing Management","address":"57 Orin Hill","city":"Madingou","state":null,"country":"Republic of the Congo","domain_name":"alibaba.com"},
    {"name":"Zooxo","registered_number":4889299,"industry":"Property-Casualty Insurers","address":"590 Autumn Leaf Lane","city":"Yurimaguas","state":null,"country":"Peru","domain_name":"nps.gov"},
    {"name":"Mycat","registered_number":3529024,"industry":"Integrated oil Companies","address":"15 Arizona Lane","city":"Huansheng","state":null,"country":"China","domain_name":"ow.ly"},
    {"name":"Teklist","registered_number":4297670,"industry":"Major Pharmaceuticals","address":"57353 Bunker Hill Lane","city":"Yuncao","state":null,"country":"China","domain_name":"epa.gov"},
    {"name":"Skidoo","registered_number":4030454,"industry":"n/a","address":"9 Ruskin Parkway","city":"Fornelos","state":"Vila Real","country":"Portugal","domain_name":"histats.com"},
    {"name":"Devpoint","registered_number":3097980,"industry":"Industrial Specialties","address":"7805 Carioca Terrace","city":"Rehoboth","state":null,"country":"Namibia","domain_name":"independent.co.uk"},
    {"name":"Zava","registered_number":1638372,"industry":"EDP Services","address":"4762 Hudson Terrace","city":"Matsumoto","state":null,"country":"Japan","domain_name":"g.co"},
    {"name":"Demizz","registered_number":2326090,"industry":"EDP Services","address":"3 Bartelt Way","city":"Arras","state":"Nord-Pas-de-Calais","country":"France","domain_name":"irs.gov"},
    {"name":"Dabjam","registered_number":2749604,"industry":"n/a","address":"533 Graceland Center","city":"Makiv","state":null,"country":"Ukraine","domain_name":"columbia.edu"},
    {"name":"Skajo","registered_number":2335555,"industry":"n/a","address":"10011 Pleasure Hill","city":"Templeogue","state":null,"country":"Ireland","domain_name":"amazon.com"},
    {"name":"Cogibox","registered_number":8447403,"industry":"Major Pharmaceuticals","address":"57 Schurz Place","city":"Khrebtovaya","state":null,"country":"Russia","domain_name":"jiathis.com"},
    {"name":"Gabtype","registered_number":2724415,"industry":"Industrial Specialties","address":"61200 Debra Circle","city":"Krzynowłoga Mała","state":null,"country":"Poland","domain_name":"yahoo.com"},
    {"name":"Browsezoom","registered_number":2437546,"industry":"Finance: Consumer Services","address":"0705 Fieldstone Point","city":"Shatura","state":null,"country":"Russia","domain_name":"sun.com"},
    {"name":"Flipstorm","registered_number":2757830,"industry":"Major Pharmaceuticals","address":"6124 Esker Street","city":"Bobo-Dioulasso","state":null,"country":"Burkina Faso","domain_name":"ucsd.edu"},
    {"name":"Twitterbridge","registered_number":9058582,"industry":"Biotechnology: Biological Products (No Diagnostic Substances)","address":"485 Schlimgen Place","city":"Canguaretama","state":null,"country":"Brazil","domain_name":"ehow.com"},
    {"name":"Topdrive","registered_number":3691488,"industry":"Coal Mining","address":"7 Pleasure Avenue","city":"Domalanoan","state":null,"country":"Philippines","domain_name":"samsung.com"},
    {"name":"Devify","registered_number":2760986,"industry":"Coal Mining","address":"0 Graedel Alley","city":"Tigarunggu","state":null,"country":"Indonesia","domain_name":"gizmodo.com"},
    {"name":"Topiczoom","registered_number":3662915,"industry":"n/a","address":"1 Bonner Pass","city":"Camatindi","state":null,"country":"Bolivia","domain_name":"xrea.com"},
    {"name":"Yata","registered_number":4408973,"industry":"Containers/Packaging","address":"154 Graceland Way","city":"Tiling","state":null,"country":"Philippines","domain_name":"naver.com"},
    {"name":"Youtags","registered_number":1673077,"industry":"Real Estate Investment Trusts","address":"92 Evergreen Avenue","city":"Đắk Glei","state":null,"country":"Vietnam","domain_name":"biglobe.ne.jp"},
    {"name":"Talane","registered_number":3150202,"industry":"Real Estate Investment Trusts","address":"33 Hallows Drive","city":"Cimadang","state":null,"country":"Indonesia","domain_name":"cnn.com"},
    {"name":"Yacero","registered_number":9132440,"industry":"Computer peripheral equipment","address":"21099 Hansons Junction","city":"Ghouazi","state":null,"country":"Morocco","domain_name":"stanford.edu"},
    {"name":"Mydo","registered_number":4139875,"industry":"Property-Casualty Insurers","address":"58796 West Alley","city":"Mulhouse","state":"Alsace","country":"France","domain_name":"liveinternet.ru"},
    {"name":"Photofeed","registered_number":6445853,"industry":"Books","address":"8318 Susan Center","city":"Lysychovo","state":null,"country":"Ukraine","domain_name":"cocolog-nifty.com"},
    {"name":"Youfeed","registered_number":9701754,"industry":"Major Banks","address":"0 Vahlen Hill","city":"Toride","state":null,"country":"Japan","domain_name":"slideshare.net"},
    {"name":"Kare","registered_number":4038804,"industry":"Electric Utilities: Central","address":"2 Gale Alley","city":"Jindong","state":null,"country":"China","domain_name":"bloglines.com"},
    {"name":"Mycat","registered_number":7047933,"industry":"Trucking Freight/Courier Services","address":"9 Hoffman Way","city":"Glinka","state":null,"country":"Russia","domain_name":"eventbrite.com"}]